Metadata-Version: 1.1
Name: tanaod
Version: 0.0.2
Summary: First libary from tanaod
Home-page: https://github.com/tanupat085/tanaodlib
Author: tanaod
Author-email: tanupat085@gmail.com
License: MIT
Download-URL: https://github.com/tanupat085/tanaodlib/archive/v0.0.2.zip
Keywords: tanaod,oop,Tanupat Satitvattana
Platform: UNKNOWN
Classifier: Development Status :: 3 - Alpha
Classifier: Intended Audience :: Education
Classifier: Topic :: Software Development :: Build Tools
Classifier: License :: OSI Approved :: MIT License
Classifier: Programming Language :: Python :: 3
Classifier: Programming Language :: Python :: 3.4
Classifier: Programming Language :: Python :: 3.5
Classifier: Programming Language :: Python :: 3.6
Classifier: Programming Language :: Python :: 3.7
Classifier: Programming Language :: Python :: 3.8
Classifier: Programming Language :: Python :: 3.9
